scaffold/__init__.py
scaffold/di.py
scaffold/email_notification_service.py
scaffold/mail_sender.py
scaffold/password_hasher.py
scaffold/pub_sub.py
scaffold/py.typed
scaffold/task_queue.py
scaffold/utils.py
scaffold/uuid7.py
scaffold/persistence/__init__.py
scaffold/persistence/model.py
scaffold/persistence/repository.py
scaffold/persistence/uow.py
scaffold/task_manager/__init__.py
scaffold/task_manager/asyncio_task_manager.py
scaffold/task_manager/quart_task_manager.py
scaffold/web/__init__.py
scaffold/web/assets.py
scaffold/web/base_app.py
scaffold/web/base_controller.py
scaffold/web/decorators.py
scaffold/web/dev_server.py
scaffold/web/forms.py
scaffold/web/typing.py
scaffold_framework-0.9.2.dist-info/METADATA
scaffold_framework-0.9.2.dist-info/WHEEL
scaffold_framework-0.9.2.dist-info/licenses/LICENSE
scaffold_framework-0.9.2.dist-info/RECORD
